dkdbutils/__init__.py
dkdbutils/esclient.py
dkdbutils/main.py
dkdbutils/migrations.py
dkdbutils/root.py
dkdbutils-0.0.25.dist-info/METADATA
dkdbutils-0.0.25.dist-info/WHEEL
dkdbutils-0.0.25.dist-info/entry_points.txt
dkdbutils-0.0.25.dist-info/top_level.txt
dkdbutils-0.0.25.dist-info/zip-safe
dkdbutils-0.0.25.dist-info/RECORD
