Metadata-Version: 2.4
Name: dkdbutils
Version: 0.0.25
Summary: Common DB utils and access libs and patterns for dagknows services
Home-page: https://github.com/dagknows/dkdbutils
Author: Sriram Panyam
Author-email: sri@dagknows.com
License: BSD 3-Clause License
Keywords: deployment tools,cli,api,setuptools
Classifier: License :: OSI Approved :: BSD License
Classifier: Programming Language :: Python :: 3
Requires-Dist: requests
Requires-Dist: typer[all]
